opentps/core/__init__.py
opentps/core/_api.py
opentps/core/_event.py
opentps/core/_loggingConfig.py
opentps/core/config/__init__.py
opentps/core/config/config_template.cfg
opentps/core/config/logger/__init__.py
opentps/core/config/logger/logging_config.json
opentps/core/config/logger/README.md
opentps/core/data/__init__.py
opentps/core/data/_dvh.py
opentps/core/data/_dvhBand.py
opentps/core/data/_patient.py
opentps/core/data/_patientData.py
opentps/core/data/_patientList.py
opentps/core/data/_roiContour.py
opentps/core/data/_rtStruct.py
opentps/core/data/_sparseBeamlets.py
opentps/core/data/_transform3D.py
opentps/core/data/CTCalibrations/__init__.py
opentps/core/data/CTCalibrations/_abstractCTCalibration.py
opentps/core/data/CTCalibrations/_piecewiseHU2Density.py
opentps/core/data/CTCalibrations/MCsquareCalibration/__init__.py
opentps/core/data/CTCalibrations/MCsquareCalibration/_G4StopPow.py
opentps/core/data/CTCalibrations/MCsquareCalibration/_mcsquareCTCalibration.py
opentps/core/data/CTCalibrations/MCsquareCalibration/_mcsquareElement.py
opentps/core/data/CTCalibrations/MCsquareCalibration/_mcsquareHU2Material.py
opentps/core/data/CTCalibrations/MCsquareCalibration/_mcsquareMaterial.py
opentps/core/data/CTCalibrations/MCsquareCalibration/_mcsquareMolecule.py
opentps/core/data/CTCalibrations/RayStationCalibration/__init__.py
opentps/core/data/CTCalibrations/RayStationCalibration/_rayStationCTCalibration.py
opentps/core/data/CTCalibrations/RayStationCalibration/_rayStationDensity2Material.py
opentps/core/data/CTCalibrations/RayStationCalibration/_rayStationMaterial.py
opentps/core/data/CTCalibrations/RayStationCalibration/_X0.py
opentps/core/data/dynamicData/__init__.py
opentps/core/data/dynamicData/_breathingSignals.py
opentps/core/data/dynamicData/_dynamic2DModel.py
opentps/core/data/dynamicData/_dynamic2DSequence.py
opentps/core/data/dynamicData/_dynamic3DModel.py
opentps/core/data/dynamicData/_dynamic3DSequence.py
opentps/core/data/images/__init__.py
opentps-3.0.0.dist-info/entry_points.txt
opentps-3.0.0.dist-info/licenses/LICENSE
opentps-3.0.0.dist-info/METADATA
opentps-3.0.0.dist-info/WHEEL
opentps-3.0.0.dist-info/RECORD
